perftester/__init__.py
perftester/__main__.py
perftester/perftester.py
perftester/tmp_singleton.py
perftester-0.7.0.dist-info/LICENSE
perftester-0.7.0.dist-info/METADATA
perftester-0.7.0.dist-info/WHEEL
perftester-0.7.0.dist-info/entry_points.txt
perftester-0.7.0.dist-info/top_level.txt
perftester-0.7.0.dist-info/RECORD
