Metadata-Version: 2.1
Name: perftester
Version: 0.7.0
Summary: Lightweight performance testing in Python
Home-page: https://github.com/nyggus/perftester
Author: Nyggus
Author-email: nyggus@gmail.com
License: UNKNOWN
Platform: UNKNOWN
Classifier: Programming Language :: Python :: 3
Classifier: License :: OSI Approved :: MIT License
Classifier: Operating System :: OS Independent
Requires-Python: >=3.8
Requires-Dist: easycheck
Requires-Dist: memory-profiler
Requires-Dist: pympler
Requires-Dist: rounder
Provides-Extra: dev
Requires-Dist: black ; extra == 'dev'
Requires-Dist: wheel ; extra == 'dev'
